weightwatcher/RMT_Util.py
weightwatcher/WW_powerlaw.py
weightwatcher/__init__.py
weightwatcher/__main__.py
weightwatcher/constants.py
weightwatcher/weightwatcher.py
weightwatcher-0.7.6.dist-info/licenses/LICENSE.txt
weightwatcher-0.7.6.dist-info/METADATA
weightwatcher-0.7.6.dist-info/WHEEL
weightwatcher-0.7.6.dist-info/entry_points.txt
weightwatcher-0.7.6.dist-info/top_level.txt
weightwatcher-0.7.6.dist-info/RECORD
