Metadata-Version: 2.4
Name: weightwatcher
Version: 0.7.6
Summary: Diagnostic Tool for Deep Neural Networks
Home-page: https://calculationconsulting.com/
Author: Calculation Consulting
Author-email: info@calculationconsulting.com
Maintainer: Calculation Consulting
Maintainer-email: info@calculationconsulting.com
License: Apache License, Version 2.0
Project-URL: Documentation, https://calculationconsulting.com/
Project-URL: Code, https://github.com/calculatedcontent/weightwatcher
Project-URL: Issue tracker, https://github.com/calculatedcontent/weightwatcher/issues
Keywords: Deep Learning Keras Tensorflow pytorch Deep Learning DNN Neural Networks
Classifier: Development Status :: 3 - Alpha
Classifier: Intended Audience :: Developers
Classifier: Intended Audience :: Education
Classifier: Intended Audience :: Science/Research
Classifier: License :: OSI Approved :: Apache Software License
Classifier: Operating System :: OS Independent
Classifier: Topic :: Scientific/Engineering :: Artificial Intelligence
Classifier: Programming Language :: Python
Classifier: Programming Language :: Python :: 3.7
Requires-Python: >= 3.3
License-File: LICENSE.txt
Requires-Dist: numpy
Requires-Dist: pandas
Requires-Dist: matplotlib
Requires-Dist: matplotlib-inline
Requires-Dist: powerlaw
Requires-Dist: scikit-learn
Requires-Dist: safetensors
Requires-Dist: tqdm
Dynamic: author
Dynamic: author-email
Dynamic: classifier
Dynamic: description
Dynamic: description-content-type
Dynamic: home-page
Dynamic: keywords
Dynamic: license
Dynamic: license-file
Dynamic: maintainer
Dynamic: maintainer-email
Dynamic: project-url
Dynamic: requires-dist
Dynamic: requires-python
Dynamic: summary
